guidebox/__init__.py
guidebox/api_requestor.py
guidebox/compat.py
guidebox/error.py
guidebox/resource.py
guidebox/version.py
guidebox-1.0.3.dist-info/LICENSE
guidebox-1.0.3.dist-info/METADATA
guidebox-1.0.3.dist-info/WHEEL
guidebox-1.0.3.dist-info/top_level.txt
guidebox-1.0.3.dist-info/RECORD
